{
  "errors": [],
  "warnings": [
    {
      "type": "missing_hook_group",
      "hook": "graphql_get_extensions",
      "file": "plugins/wp-graphql/src/Admin/Extensions/Extensions.php",
      "line": 402,
      "message": "Missing @hookGroup tag"
    },
    {
      "type": "missing_hook_since",
      "hook": "graphql_get_extensions",
      "file": "plugins/wp-graphql/src/Admin/Extensions/Extensions.php",
      "line": 402,
      "message": "Missing @since tag in nearest docblock"
    },
    {
      "type": "missing_hook_group",
      "hook": "graphql_init_request",
      "file": "plugins/wp-graphql/src/CLI/Commands.php",
      "line": 70,
      "message": "Missing @hookGroup tag"
    },
    {
      "type": "missing_hook_group",
      "hook": "graphql_menu_item_connection_args",
      "file": "plugins/wp-graphql/src/Data/Connection/MenuItemConnectionResolver.php",
      "line": 107,
      "message": "Missing @hookGroup tag"
    },
    {
      "type": "missing_hook_group",
      "hook": "graphql_map_input_fields_to_wp_user_query",
      "file": "plugins/wp-graphql/src/Data/Connection/UserConnectionResolver.php",
      "line": 260,
      "message": "Missing @hookGroup tag"
    },
    {
      "type": "missing_hook_group",
      "hook": "graphql_pre_comment_cursor_node",
      "file": "plugins/wp-graphql/src/Data/Cursor/CommentObjectCursor.php",
      "line": 64,
      "message": "Missing @hookGroup tag"
    },
    {
      "type": "missing_hook_since",
      "hook": "graphql_pre_comment_cursor_node",
      "file": "plugins/wp-graphql/src/Data/Cursor/CommentObjectCursor.php",
      "line": 64,
      "message": "Missing @since tag in nearest docblock"
    },
    {
      "type": "missing_hook_group",
      "hook": "graphql_cursor_ordering_field",
      "file": "plugins/wp-graphql/src/Data/Cursor/CursorBuilder.php",
      "line": 58,
      "message": "Missing @hookGroup tag"
    },
    {
      "type": "missing_hook_since",
      "hook": "graphql_cursor_ordering_field",
      "file": "plugins/wp-graphql/src/Data/Cursor/CursorBuilder.php",
      "line": 58,
      "message": "Missing @since tag in nearest docblock"
    },
    {
      "type": "missing_hook_group",
      "hook": "graphql_pre_term_cursor_node",
      "file": "plugins/wp-graphql/src/Data/Cursor/TermObjectCursor.php",
      "line": 48,
      "message": "Missing @hookGroup tag"
    },
    {
      "type": "missing_hook_since",
      "hook": "graphql_pre_term_cursor_node",
      "file": "plugins/wp-graphql/src/Data/Cursor/TermObjectCursor.php",
      "line": 48,
      "message": "Missing @since tag in nearest docblock"
    },
    {
      "type": "missing_hook_group",
      "hook": "graphql_pre_user_cursor_node",
      "file": "plugins/wp-graphql/src/Data/Cursor/UserCursor.php",
      "line": 83,
      "message": "Missing @hookGroup tag"
    },
    {
      "type": "missing_hook_since",
      "hook": "graphql_pre_user_cursor_node",
      "file": "plugins/wp-graphql/src/Data/Cursor/UserCursor.php",
      "line": 83,
      "message": "Missing @since tag in nearest docblock"
    },
    {
      "type": "missing_hook_group",
      "hook": "graphql_term_object_insert_term_args",
      "file": "plugins/wp-graphql/src/Data/TermObjectMutation.php",
      "line": 108,
      "message": "Missing @hookGroup tag"
    },
    {
      "type": "missing_hook_since",
      "hook": "graphql_term_object_insert_term_args",
      "file": "plugins/wp-graphql/src/Data/TermObjectMutation.php",
      "line": 108,
      "message": "Missing @since tag in nearest docblock"
    },
    {
      "type": "missing_hook_group",
      "hook": "graphql_should_show_experiments_in_extensions",
      "file": "plugins/wp-graphql/src/Experimental/Extensions.php",
      "line": 57,
      "message": "Missing @hookGroup tag"
    },
    {
      "type": "missing_hook_since",
      "hook": "graphql_should_show_experiments_in_extensions",
      "file": "plugins/wp-graphql/src/Experimental/Extensions.php",
      "line": 57,
      "message": "Missing @since tag in nearest docblock"
    },
    {
      "type": "missing_hook_group",
      "hook": "graphql_media_item_create_allowed_protocols",
      "file": "plugins/wp-graphql/src/Mutation/MediaItemCreate.php",
      "line": 210,
      "message": "Missing @hookGroup tag"
    },
    {
      "type": "missing_hook_since",
      "hook": "graphql_media_item_create_allowed_protocols",
      "file": "plugins/wp-graphql/src/Mutation/MediaItemCreate.php",
      "line": 210,
      "message": "Missing @since tag in nearest docblock"
    },
    {
      "type": "missing_hook_group",
      "hook": "graphql_pre_resolve_menu_item_connected_node",
      "file": "plugins/wp-graphql/src/Type/ObjectType/MenuItem.php",
      "line": 57,
      "message": "Missing @hookGroup tag"
    },
    {
      "type": "missing_hook_since",
      "hook": "graphql_pre_resolve_menu_item_connected_node",
      "file": "plugins/wp-graphql/src/Type/ObjectType/MenuItem.php",
      "line": 57,
      "message": "Missing @since tag in nearest docblock"
    },
    {
      "type": "missing_hook_group",
      "hook": "graphql_type_interfaces",
      "file": "plugins/wp-graphql/src/Type/WPInterfaceTrait.php",
      "line": 37,
      "message": "Missing @hookGroup tag"
    },
    {
      "type": "missing_hook_since",
      "hook": "graphql_type_interfaces",
      "file": "plugins/wp-graphql/src/Type/WPInterfaceTrait.php",
      "line": 37,
      "message": "Missing @since tag in nearest docblock"
    },
    {
      "type": "missing_hook_group",
      "hook": "graphql_resolve_revision_meta_from_parent",
      "file": "plugins/wp-graphql/src/Utils/Preview.php",
      "line": 37,
      "message": "Missing @hookGroup tag"
    },
    {
      "type": "missing_hook_since",
      "hook": "graphql_resolve_revision_meta_from_parent",
      "file": "plugins/wp-graphql/src/Utils/Preview.php",
      "line": 37,
      "message": "Missing @since tag in nearest docblock"
    },
    {
      "type": "missing_hook_group",
      "hook": "graphql_schema_config",
      "file": "plugins/wp-graphql/src/WPSchema.php",
      "line": 52,
      "message": "Missing @hookGroup tag"
    }
  ]
}
