{
  "plugin": "wp-graphql",
  "generatedAt": "2026-04-16T20:31:53.028Z",
  "count": 21,
  "hooks": [
    {
      "pluginSlug": "wp-graphql",
      "name": "do_graphql_request",
      "kind": "action",
      "group": "uncategorized",
      "groupLabel": "Uncategorized",
      "groupSource": "fallback",
      "sourceType": "wpgraphql",
      "emitter": "do_action_deprecated",
      "file": "plugins/wp-graphql/src/Request.php",
      "line": 613,
      "description": "Legacy GraphQL request lifecycle action retained for backward compatibility.",
      "params": [],
      "argumentCount": 3,
      "docblockParamCount": 0,
      "since": "0.0.5",
      "hookGroup": null,
      "isDynamic": false,
      "rawExpression": "'do_graphql_request'",
      "relatedSnippets": [],
      "lifecycle": {
        "status": "deprecated",
        "deprecatedIn": "x-release-please-version",
        "removedIn": null,
        "replacement": "graphql_do_request",
        "message": null,
        "source": "deprecated_call"
      },
      "sourceLocations": [
        {
          "file": "plugins/wp-graphql/src/Request.php",
          "line": 613
        }
      ],
      "occurrences": 1
    },
    {
      "pluginSlug": "wp-graphql",
      "name": "enqueue_graphiql_extension",
      "kind": "action",
      "group": "uncategorized",
      "groupLabel": "Uncategorized",
      "groupSource": "fallback",
      "sourceType": "wpgraphql",
      "emitter": "do_action_deprecated",
      "file": "plugins/wp-graphql/src/Admin/GraphiQL/GraphiQL.php",
      "line": 315,
      "description": "Legacy GraphiQL extension enqueue action retained for backward compatibility.",
      "params": [],
      "argumentCount": 3,
      "docblockParamCount": 0,
      "since": null,
      "hookGroup": null,
      "isDynamic": false,
      "rawExpression": "'enqueue_graphiql_extension'",
      "relatedSnippets": [],
      "lifecycle": {
        "status": "deprecated",
        "deprecatedIn": "x-release-please-version",
        "removedIn": null,
        "replacement": "graphql_enqueue_graphiql_extension",
        "message": null,
        "source": "deprecated_call"
      },
      "sourceLocations": [
        {
          "file": "plugins/wp-graphql/src/Admin/GraphiQL/GraphiQL.php",
          "line": 315
        }
      ],
      "occurrences": 1
    },
    {
      "pluginSlug": "wp-graphql",
      "name": "graphql_connection",
      "kind": "filter",
      "group": "uncategorized",
      "groupLabel": "Uncategorized",
      "groupSource": "fallback",
      "sourceType": "wpgraphql",
      "emitter": "apply_filters_deprecated",
      "file": "plugins/wp-graphql/src/Data/Connection/AbstractConnectionResolver.php",
      "line": 1043,
      "description": "Legacy connection result filter retained for backward compatibility.",
      "params": [],
      "argumentCount": 3,
      "docblockParamCount": 0,
      "since": null,
      "hookGroup": null,
      "isDynamic": false,
      "rawExpression": "'graphql_connection'",
      "relatedSnippets": [],
      "lifecycle": {
        "status": "deprecated",
        "deprecatedIn": "x-release-please-version",
        "removedIn": null,
        "replacement": "graphql_connection_resolved",
        "message": null,
        "source": "deprecated_call"
      },
      "sourceLocations": [
        {
          "file": "plugins/wp-graphql/src/Data/Connection/AbstractConnectionResolver.php",
          "line": 1043
        }
      ],
      "occurrences": 1
    },
    {
      "pluginSlug": "wp-graphql",
      "name": "graphql_data_loaders",
      "kind": "filter",
      "group": "uncategorized",
      "groupLabel": "Uncategorized",
      "groupSource": "fallback",
      "sourceType": "wpgraphql",
      "emitter": "apply_filters_deprecated",
      "file": "plugins/wp-graphql/src/AppContext.php",
      "line": 219,
      "description": "",
      "params": [
        {
          "type": "array<string,\\WPGraphQL\\Data\\Loader\\AbstractDataLoader>",
          "name": "$loaders",
          "description": "The loaders accessible in the AppContext"
        },
        {
          "type": "\\WPGraphQL\\AppContext",
          "name": "$context",
          "description": "The AppContext"
        }
      ],
      "argumentCount": 4,
      "docblockParamCount": 2,
      "since": null,
      "hookGroup": null,
      "isDynamic": false,
      "rawExpression": "'graphql_data_loaders'",
      "relatedSnippets": [],
      "lifecycle": {
        "status": "deprecated",
        "deprecatedIn": "2.3.2",
        "removedIn": null,
        "replacement": "graphql_data_loader_classes",
        "message": null,
        "source": "deprecated_call"
      },
      "sourceLocations": [
        {
          "file": "plugins/wp-graphql/src/AppContext.php",
          "line": 219
        }
      ],
      "occurrences": 1
    },
    {
      "pluginSlug": "wp-graphql",
      "name": "graphql_endpoint",
      "kind": "filter",
      "group": "settings",
      "groupLabel": "Settings and Admin",
      "groupSource": "fallback",
      "sourceType": "wpgraphql",
      "emitter": "apply_filters_deprecated",
      "file": "plugins/wp-graphql/src/Admin/Settings/Settings.php",
      "line": 103,
      "description": "Legacy endpoint path filter retained for backward compatibility.",
      "params": [],
      "argumentCount": 3,
      "docblockParamCount": 0,
      "since": "1.12.0",
      "hookGroup": null,
      "isDynamic": false,
      "rawExpression": "'graphql_endpoint'",
      "relatedSnippets": [],
      "lifecycle": {
        "status": "deprecated",
        "deprecatedIn": "x-release-please-version",
        "removedIn": null,
        "replacement": "graphql_endpoint_path",
        "message": null,
        "source": "deprecated_call"
      },
      "sourceLocations": [
        {
          "file": "plugins/wp-graphql/src/Admin/Settings/Settings.php",
          "line": 103
        },
        {
          "file": "plugins/wp-graphql/access-functions.php",
          "line": 902
        }
      ],
      "occurrences": 2
    },
    {
      "pluginSlug": "wp-graphql",
      "name": "graphql_execute",
      "kind": "action",
      "group": "request-lifecycle",
      "groupLabel": "Request Lifecycle",
      "groupSource": "fallback",
      "sourceType": "wpgraphql",
      "emitter": "do_action_deprecated",
      "file": "plugins/wp-graphql/src/Request.php",
      "line": 521,
      "description": "Legacy GraphQL request execution action retained for backward compatibility.",
      "params": [],
      "argumentCount": 3,
      "docblockParamCount": 0,
      "since": "0.0.4",
      "hookGroup": null,
      "isDynamic": false,
      "rawExpression": "'graphql_execute'",
      "relatedSnippets": [],
      "lifecycle": {
        "status": "deprecated",
        "deprecatedIn": "x-release-please-version",
        "removedIn": null,
        "replacement": "graphql_request_execute",
        "message": null,
        "source": "deprecated_call"
      },
      "sourceLocations": [
        {
          "file": "plugins/wp-graphql/src/Request.php",
          "line": 521
        }
      ],
      "occurrences": 1
    },
    {
      "pluginSlug": "wp-graphql",
      "name": "graphql_object_type_interfaces",
      "kind": "filter",
      "group": "models",
      "groupLabel": "Model Layer",
      "groupSource": "fallback",
      "sourceType": "wpgraphql",
      "emitter": "apply_filters_deprecated",
      "file": "plugins/wp-graphql/src/Deprecated.php",
      "line": 63,
      "description": "",
      "params": [
        {
          "type": "string[]",
          "name": "$interfaces",
          "description": "List of interfaces applied to the Object Type"
        },
        {
          "type": "array<string,mixed>",
          "name": "$config",
          "description": "The config for the Object Type"
        },
        {
          "type": "\\WPGraphQL\\Type\\WPInterfaceType|\\WPGraphQL\\Type\\WPObjectType",
          "name": "$type",
          "description": "The Type instance"
        }
      ],
      "argumentCount": 4,
      "docblockParamCount": 3,
      "since": null,
      "hookGroup": null,
      "isDynamic": false,
      "rawExpression": "'graphql_object_type_interfaces'",
      "relatedSnippets": [],
      "lifecycle": {
        "status": "deprecated",
        "deprecatedIn": "1.4.1",
        "removedIn": null,
        "replacement": "graphql_type_interfaces",
        "message": null,
        "source": "deprecated_call"
      },
      "sourceLocations": [
        {
          "file": "plugins/wp-graphql/src/Deprecated.php",
          "line": 63
        }
      ],
      "occurrences": 1
    },
    {
      "pluginSlug": "wp-graphql",
      "name": "graphql_resolve_menu_item",
      "kind": "filter",
      "group": "uncategorized",
      "groupLabel": "Uncategorized",
      "groupSource": "fallback",
      "sourceType": "wpgraphql",
      "emitter": "apply_filters_deprecated",
      "file": "plugins/wp-graphql/src/Deprecated.php",
      "line": 165,
      "description": "",
      "params": [
        {
          "type": "\\WP_Post|\\WP_Term",
          "name": "$resolved_object",
          "description": "Post or term connected to MenuItem"
        },
        {
          "type": "array<string,mixed>",
          "name": "$args",
          "description": "Array of arguments input in the field as part of the GraphQL query"
        },
        {
          "type": "\\WPGraphQL\\AppContext",
          "name": "$context",
          "description": "Object containing app context that gets passed down the resolve tree"
        },
        {
          "type": "\\GraphQL\\Type\\Definition\\ResolveInfo",
          "name": "$info",
          "description": "Info about fields passed down the resolve tree"
        },
        {
          "type": "int",
          "name": "$object_id",
          "description": "Post or term ID of connected object"
        },
        {
          "type": "string",
          "name": "$object_type",
          "description": "Type of connected object (\"post_type\" or \"taxonomy\")"
        }
      ],
      "argumentCount": 4,
      "docblockParamCount": 6,
      "since": "0.0.30",
      "hookGroup": null,
      "isDynamic": false,
      "rawExpression": "'graphql_resolve_menu_item'",
      "relatedSnippets": [],
      "lifecycle": {
        "status": "deprecated",
        "deprecatedIn": "1.22.0",
        "removedIn": null,
        "replacement": "graphql_pre_resolve_menu_item_connected_node",
        "message": null,
        "source": "deprecated_call"
      },
      "sourceLocations": [
        {
          "file": "plugins/wp-graphql/src/Deprecated.php",
          "line": 165
        }
      ],
      "occurrences": 1
    },
    {
      "pluginSlug": "wp-graphql",
      "name": "graphql_return_modeled_data",
      "kind": "filter",
      "group": "uncategorized",
      "groupLabel": "Uncategorized",
      "groupSource": "fallback",
      "sourceType": "wpgraphql",
      "emitter": "apply_filters_deprecated",
      "file": "plugins/wp-graphql/src/Deprecated.php",
      "line": 91,
      "description": "",
      "params": [
        {
          "type": "array<string,mixed>",
          "name": "$fields",
          "description": "The array of fields for the model"
        },
        {
          "type": "string",
          "name": "$model_name",
          "description": "Name of the model the filter is currently being executed in"
        },
        {
          "type": "string",
          "name": "$visibility",
          "description": "The visibility setting for this piece of data"
        },
        {
          "type": "?int",
          "name": "$owner",
          "description": "The user ID for the owner of this piece of data"
        },
        {
          "type": "\\WP_User",
          "name": "$current_user",
          "description": "The current user for the session"
        }
      ],
      "argumentCount": 4,
      "docblockParamCount": 5,
      "since": null,
      "hookGroup": null,
      "isDynamic": false,
      "rawExpression": "'graphql_return_modeled_data'",
      "relatedSnippets": [],
      "lifecycle": {
        "status": "deprecated",
        "deprecatedIn": "1.7.0",
        "removedIn": null,
        "replacement": "graphql_model_prepare_fields",
        "message": null,
        "source": "deprecated_call"
      },
      "sourceLocations": [
        {
          "file": "plugins/wp-graphql/src/Deprecated.php",
          "line": 91
        }
      ],
      "occurrences": 1
    },
    {
      "pluginSlug": "wp-graphql",
      "name": "graphql_schema",
      "kind": "filter",
      "group": "uncategorized",
      "groupLabel": "Uncategorized",
      "groupSource": "fallback",
      "sourceType": "wpgraphql",
      "emitter": "apply_filters_deprecated",
      "file": "plugins/wp-graphql/src/Registry/SchemaRegistry.php",
      "line": 84,
      "description": "Legacy schema filter retained for backward compatibility.",
      "params": [],
      "argumentCount": 3,
      "docblockParamCount": 0,
      "since": "0.0.5",
      "hookGroup": null,
      "isDynamic": false,
      "rawExpression": "'graphql_schema'",
      "relatedSnippets": [],
      "lifecycle": {
        "status": "deprecated",
        "deprecatedIn": "x-release-please-version",
        "removedIn": null,
        "replacement": "graphql_schema_instance",
        "message": null,
        "source": "deprecated_call"
      },
      "sourceLocations": [
        {
          "file": "plugins/wp-graphql/src/Registry/SchemaRegistry.php",
          "line": 84
        },
        {
          "file": "plugins/wp-graphql/src/WPGraphQL.php",
          "line": 926
        }
      ],
      "occurrences": 2
    },
    {
      "pluginSlug": "wp-graphql",
      "name": "init_graphql_request",
      "kind": "action",
      "group": "uncategorized",
      "groupLabel": "Uncategorized",
      "groupSource": "fallback",
      "sourceType": "wpgraphql",
      "emitter": "do_action_deprecated",
      "file": "plugins/wp-graphql/src/CLI/Commands.php",
      "line": 72,
      "description": "Legacy request initialization hook retained for backward compatibility.",
      "params": [],
      "argumentCount": 3,
      "docblockParamCount": 0,
      "since": "0.0.5",
      "hookGroup": null,
      "isDynamic": false,
      "rawExpression": "'init_graphql_request'",
      "relatedSnippets": [],
      "lifecycle": {
        "status": "deprecated",
        "deprecatedIn": "x-release-please-version",
        "removedIn": null,
        "replacement": "graphql_init_request",
        "message": null,
        "source": "deprecated_call"
      },
      "sourceLocations": [
        {
          "file": "plugins/wp-graphql/src/CLI/Commands.php",
          "line": 72
        },
        {
          "file": "plugins/wp-graphql/src/Request.php",
          "line": 163
        }
      ],
      "occurrences": 2
    },
    {
      "pluginSlug": "wp-graphql",
      "name": "init_graphql_type_registry",
      "kind": "action",
      "group": "uncategorized",
      "groupLabel": "Uncategorized",
      "groupSource": "fallback",
      "sourceType": "wpgraphql",
      "emitter": "do_action_deprecated",
      "file": "plugins/wp-graphql/src/Registry/TypeRegistry.php",
      "line": 283,
      "description": "Legacy type registry initialization hook retained for backward compatibility.",
      "params": [],
      "argumentCount": 3,
      "docblockParamCount": 0,
      "since": null,
      "hookGroup": null,
      "isDynamic": false,
      "rawExpression": "'init_graphql_type_registry'",
      "relatedSnippets": [],
      "lifecycle": {
        "status": "deprecated",
        "deprecatedIn": "x-release-please-version",
        "removedIn": null,
        "replacement": "graphql_init_type_registry",
        "message": null,
        "source": "deprecated_call"
      },
      "sourceLocations": [
        {
          "file": "plugins/wp-graphql/src/Registry/TypeRegistry.php",
          "line": 283
        }
      ],
      "occurrences": 1
    },
    {
      "pluginSlug": "wp-graphql",
      "name": "pre_graphql_execute_request",
      "kind": "filter",
      "group": "uncategorized",
      "groupLabel": "Uncategorized",
      "groupSource": "fallback",
      "sourceType": "wpgraphql",
      "emitter": "apply_filters_deprecated",
      "file": "plugins/wp-graphql/src/Request.php",
      "line": 696,
      "description": "Legacy pre-execute request filter retained for backward compatibility.",
      "params": [],
      "argumentCount": 3,
      "docblockParamCount": 0,
      "since": null,
      "hookGroup": null,
      "isDynamic": false,
      "rawExpression": "'pre_graphql_execute_request'",
      "relatedSnippets": [],
      "lifecycle": {
        "status": "deprecated",
        "deprecatedIn": "x-release-please-version",
        "removedIn": null,
        "replacement": "graphql_pre_execute_request",
        "message": null,
        "source": "deprecated_call"
      },
      "sourceLocations": [
        {
          "file": "plugins/wp-graphql/src/Request.php",
          "line": 696
        },
        {
          "file": "plugins/wp-graphql/src/Request.php",
          "line": 811
        }
      ],
      "occurrences": 2
    },
    {
      "pluginSlug": "wp-graphql",
      "name": "register_graphql_post_type_args",
      "kind": "filter",
      "group": "uncategorized",
      "groupLabel": "Uncategorized",
      "groupSource": "fallback",
      "sourceType": "wpgraphql",
      "emitter": "apply_filters_deprecated",
      "file": "plugins/wp-graphql/src/WPGraphQL.php",
      "line": 626,
      "description": "Legacy post type registration filter retained for backward compatibility.",
      "params": [],
      "argumentCount": 3,
      "docblockParamCount": 0,
      "since": "1.12.0",
      "hookGroup": null,
      "isDynamic": false,
      "rawExpression": "'register_graphql_post_type_args'",
      "relatedSnippets": [],
      "lifecycle": {
        "status": "deprecated",
        "deprecatedIn": "x-release-please-version",
        "removedIn": null,
        "replacement": "graphql_register_post_type_args",
        "message": null,
        "source": "deprecated_call"
      },
      "sourceLocations": [
        {
          "file": "plugins/wp-graphql/src/WPGraphQL.php",
          "line": 626
        }
      ],
      "occurrences": 1
    },
    {
      "pluginSlug": "wp-graphql",
      "name": "register_graphql_taxonomy_args",
      "kind": "filter",
      "group": "uncategorized",
      "groupLabel": "Uncategorized",
      "groupSource": "fallback",
      "sourceType": "wpgraphql",
      "emitter": "apply_filters_deprecated",
      "file": "plugins/wp-graphql/src/WPGraphQL.php",
      "line": 665,
      "description": "Legacy taxonomy registration filter retained for backward compatibility.",
      "params": [],
      "argumentCount": 3,
      "docblockParamCount": 0,
      "since": "1.12.0",
      "hookGroup": null,
      "isDynamic": false,
      "rawExpression": "'register_graphql_taxonomy_args'",
      "relatedSnippets": [],
      "lifecycle": {
        "status": "deprecated",
        "deprecatedIn": "x-release-please-version",
        "removedIn": null,
        "replacement": "graphql_register_taxonomy_args",
        "message": null,
        "source": "deprecated_call"
      },
      "sourceLocations": [
        {
          "file": "plugins/wp-graphql/src/WPGraphQL.php",
          "line": 665
        }
      ],
      "occurrences": 1
    },
    {
      "pluginSlug": "wp-graphql",
      "name": "wp_graphql_experiment_config",
      "kind": "filter",
      "group": "uncategorized",
      "groupLabel": "Uncategorized",
      "groupSource": "fallback",
      "sourceType": "wpgraphql",
      "emitter": "apply_filters_deprecated",
      "file": "plugins/wp-graphql/src/Experimental/Experiment/AbstractExperiment.php",
      "line": 393,
      "description": "Legacy experiment config filter retained for backward compatibility.",
      "params": [],
      "argumentCount": 3,
      "docblockParamCount": 0,
      "since": null,
      "hookGroup": null,
      "isDynamic": false,
      "rawExpression": "'wp_graphql_experiment_config'",
      "relatedSnippets": [],
      "lifecycle": {
        "status": "deprecated",
        "deprecatedIn": "x-release-please-version",
        "removedIn": null,
        "replacement": "graphql_experiment_config",
        "message": null,
        "source": "deprecated_call"
      },
      "sourceLocations": [
        {
          "file": "plugins/wp-graphql/src/Experimental/Experiment/AbstractExperiment.php",
          "line": 393
        }
      ],
      "occurrences": 1
    },
    {
      "pluginSlug": "wp-graphql",
      "name": "wp_graphql_experiment_enabled",
      "kind": "filter",
      "group": "uncategorized",
      "groupLabel": "Uncategorized",
      "groupSource": "fallback",
      "sourceType": "wpgraphql",
      "emitter": "apply_filters_deprecated",
      "file": "plugins/wp-graphql/src/Experimental/Experiment/AbstractExperiment.php",
      "line": 328,
      "description": "Legacy experiment enabled filter retained for backward compatibility.",
      "params": [],
      "argumentCount": 3,
      "docblockParamCount": 0,
      "since": null,
      "hookGroup": null,
      "isDynamic": false,
      "rawExpression": "'wp_graphql_experiment_enabled'",
      "relatedSnippets": [],
      "lifecycle": {
        "status": "deprecated",
        "deprecatedIn": "x-release-please-version",
        "removedIn": null,
        "replacement": "graphql_experiment_enabled",
        "message": null,
        "source": "deprecated_call"
      },
      "sourceLocations": [
        {
          "file": "plugins/wp-graphql/src/Experimental/Experiment/AbstractExperiment.php",
          "line": 328
        }
      ],
      "occurrences": 1
    },
    {
      "pluginSlug": "wp-graphql",
      "name": "wpgraphql_enable_major_autoupdates",
      "kind": "filter",
      "group": "uncategorized",
      "groupLabel": "Uncategorized",
      "groupSource": "fallback",
      "sourceType": "wpgraphql",
      "emitter": "apply_filters_deprecated",
      "file": "plugins/wp-graphql/src/Admin/Updates/UpdateChecker.php",
      "line": 320,
      "description": "Legacy autoupdate filter retained for backward compatibility.",
      "params": [],
      "argumentCount": 3,
      "docblockParamCount": 0,
      "since": null,
      "hookGroup": null,
      "isDynamic": false,
      "rawExpression": "'wpgraphql_enable_major_autoupdates'",
      "relatedSnippets": [],
      "lifecycle": {
        "status": "deprecated",
        "deprecatedIn": "x-release-please-version",
        "removedIn": null,
        "replacement": "graphql_enable_major_autoupdates",
        "message": null,
        "source": "deprecated_call"
      },
      "sourceLocations": [
        {
          "file": "plugins/wp-graphql/src/Admin/Updates/UpdateChecker.php",
          "line": 320
        }
      ],
      "occurrences": 1
    },
    {
      "pluginSlug": "wp-graphql",
      "name": "wpgraphql_enable_untested_autoupdates",
      "kind": "filter",
      "group": "uncategorized",
      "groupLabel": "Uncategorized",
      "groupSource": "fallback",
      "sourceType": "wpgraphql",
      "emitter": "apply_filters_deprecated",
      "file": "plugins/wp-graphql/src/Admin/Updates/UpdateChecker.php",
      "line": 355,
      "description": "Legacy untested autoupdate filter retained for backward compatibility.",
      "params": [],
      "argumentCount": 3,
      "docblockParamCount": 0,
      "since": null,
      "hookGroup": null,
      "isDynamic": false,
      "rawExpression": "'wpgraphql_enable_untested_autoupdates'",
      "relatedSnippets": [],
      "lifecycle": {
        "status": "deprecated",
        "deprecatedIn": "x-release-please-version",
        "removedIn": null,
        "replacement": "graphql_enable_untested_autoupdates",
        "message": null,
        "source": "deprecated_call"
      },
      "sourceLocations": [
        {
          "file": "plugins/wp-graphql/src/Admin/Updates/UpdateChecker.php",
          "line": 355
        }
      ],
      "occurrences": 1
    },
    {
      "pluginSlug": "wp-graphql",
      "name": "wpgraphql_experimental_features_enabled",
      "kind": "filter",
      "group": "uncategorized",
      "groupLabel": "Uncategorized",
      "groupSource": "fallback",
      "sourceType": "wpgraphql",
      "emitter": "apply_filters_deprecated",
      "file": "plugins/wp-graphql/src/Experimental/Experimental.php",
      "line": 71,
      "description": "Legacy experimental features toggle filter retained for backward compatibility.",
      "params": [],
      "argumentCount": 3,
      "docblockParamCount": 0,
      "since": null,
      "hookGroup": null,
      "isDynamic": false,
      "rawExpression": "'wpgraphql_experimental_features_enabled'",
      "relatedSnippets": [],
      "lifecycle": {
        "status": "deprecated",
        "deprecatedIn": "x-release-please-version",
        "removedIn": null,
        "replacement": "graphql_experimental_features_enabled",
        "message": null,
        "source": "deprecated_call"
      },
      "sourceLocations": [
        {
          "file": "plugins/wp-graphql/src/Experimental/Experimental.php",
          "line": 71
        }
      ],
      "occurrences": 1
    },
    {
      "pluginSlug": "wp-graphql",
      "name": "wpgraphql_untested_release_type",
      "kind": "filter",
      "group": "uncategorized",
      "groupLabel": "Uncategorized",
      "groupSource": "fallback",
      "sourceType": "wpgraphql",
      "emitter": "apply_filters_deprecated",
      "file": "plugins/wp-graphql/src/Admin/Updates/UpdateChecker.php",
      "line": 383,
      "description": "Legacy release channel filter retained for backward compatibility.",
      "params": [],
      "argumentCount": 3,
      "docblockParamCount": 0,
      "since": null,
      "hookGroup": null,
      "isDynamic": false,
      "rawExpression": "'wpgraphql_untested_release_type'",
      "relatedSnippets": [],
      "lifecycle": {
        "status": "deprecated",
        "deprecatedIn": "x-release-please-version",
        "removedIn": null,
        "replacement": "graphql_untested_release_type",
        "message": null,
        "source": "deprecated_call"
      },
      "sourceLocations": [
        {
          "file": "plugins/wp-graphql/src/Admin/Updates/UpdateChecker.php",
          "line": 383
        }
      ],
      "occurrences": 1
    }
  ]
}
